pygmlparser/Edge.py
pygmlparser/Graph.py
pygmlparser/Node.py
pygmlparser/Parser.py
pygmlparser/__init__.py
pygmlparser/exceptions/GMLException.py
pygmlparser/exceptions/GMLParseException.py
pygmlparser/exceptions/__init__.py
pygmlparser/graphics/BaseGraphics.py
pygmlparser/graphics/EdgeGraphics.py
pygmlparser/graphics/NodeGraphics.py
pygmlparser/graphics/Point.py
pygmlparser/graphics/__init__.py
tests/PyTestTemplate.py
tests/RunTests.py
tests/TestBase.py
tests/TestEdge.py
tests/TestGraph.py
tests/TestNode.py
tests/TestParser.py
tests/__init__.py
pygmlparser-1.0.1.dist-info/LICENSE
pygmlparser-1.0.1.dist-info/METADATA
pygmlparser-1.0.1.dist-info/WHEEL
pygmlparser-1.0.1.dist-info/top_level.txt
pygmlparser-1.0.1.dist-info/RECORD
