Metadata-Version: 2.1
Name: pygmlparser
Version: 1.0.1
Summary: Graph Modeling Language (GML) standalone parser for Python 3.
Home-page: https://github.com/hasii2011/PyGMLParser
License-File: LICENSE
